movie_art/__init__.py
movie_art/__main__.py
movie_art/config.py
movie_art/constants.py
movie_art/generators.py
movie_art-0.1.1.dist-info/LICENSE
movie_art-0.1.1.dist-info/METADATA
movie_art-0.1.1.dist-info/WHEEL
movie_art-0.1.1.dist-info/RECORD
