Metadata-Version: 2.1
Name: movie-art
Version: 0.1.1
Summary: Turn your favorite movies into 1D representations using their frames' average color.
Author: Ramon Meza
Author-email: ramon_meza@live.com
Requires-Python: >=3.10,<4.0
Classifier: Programming Language :: Python :: 3
Classifier: Programming Language :: Python :: 3.10
Classifier: Programming Language :: Python :: 3.11
Requires-Dist: opencv-python (>=4.8.1.78,<5.0.0.0)
